{
	"configurations" : 
	[
		{
			"directories" : 
			[
				{
					"build" : ".",
					"jsonFile" : "directory-.-Debug-d0094a50bb2071803777.json",
					"minimumCMakeVersion" : 
					{
						"string" : "3.20"
					},
					"projectIndex" : 0,
					"source" : ".",
					"targetIndexes" : 
					[
						0
					]
				}
			],
			"name" : "Debug",
			"projects" : 
			[
				{
					"directoryIndexes" : 
					[
						0
					],
					"name" : "namespace",
					"targetIndexes" : 
					[
						0
					]
				}
			],
			"targets" : 
			[
				{
					"directoryIndex" : 0,
					"id" : "namespace::@6890427a1f51a3e7e1df",
					"jsonFile" : "target-namespace-Debug-c6f3087d89a0c381a1d4.json",
					"name" : "namespace",
					"projectIndex" : 0
				}
			]
		}
	],
	"kind" : "codemodel",
	"paths" : 
	{
		"build" : "E:/Prgramming_language/C++/cpp_seris/23_chapter10_class/build",
		"source" : "E:/Prgramming_language/C++/cpp_seris/23_chapter10_class"
	},
	"version" : 
	{
		"major" : 2,
		"minor" : 4
	}
}
